{
    "name": "",
    "description": "",
    "features": [],
    "leveled_features": [
        {
            "start_level": 2,
            "feature": "_dnd5e:features.wizard.divination.divination_savant"
        },
        {
            "start_level": 2,
            "feature": "_dnd5e:features.wizard.divination.portent"
        },
        {
            "start_level": 6,
            "feature": "_dnd5e:features.wizard.divination.expert_divination"
        },
        {
            "start_level": 10,
            "feature": "_dnd5e:features.wizard.divination.the_third_eye"
        },
        {
            "start_level": 14,
            "feature": "_dnd5e:features.wizard.divination.greater_portent"
        }
    ],
    "additional": {
        "classSource": "PHB",
        "subclassFeatures": [
            "School of Divination|Wizard||Divination||2",
            "Expert Divination|Wizard||Divination||6",
            "The Third Eye|Wizard||Divination||10",
            "Greater Portent|Wizard||Divination||14"
        ]
    }
}