{
    "name": "野蛮人",
    "description": "_dnd5e:files.babarian",
    "hp_dice": "d12",
    "features": [
        "_dnd5e:features.babarian.armor",
        "_dnd5e:features.babarian.weapons",
        "_dnd5e:features.babarian.saves",
        "_dnd5e:features.babarian.skills",
        "_dnd5e:features.babarian.rage",
        "_dnd5e:features.babarian.unarmored_defense",
        "_dnd5e:features.babarian.reckless_attack",
        "_dnd5e:features.babarian.danger_sense",
        "_dnd5e:features.babarian.primal_path"
    ],
    "equipment": [
    ]
}