{"name": "", "description": "", "category": "class_proficiencies", "effects": [{"type": "selection", "choose": 2, "available": ["_dnd5e:effects.proficiencies.skills.arcana@1", "_dnd5e:effects.proficiencies.skills.animal_handling@1", "_dnd5e:effects.proficiencies.skills.insight@1", "_dnd5e:effects.proficiencies.skills.medicine@1", "_dnd5e:effects.proficiencies.skills.nature@1", "_dnd5e:effects.proficiencies.skills.perception@1", "_dnd5e:effects.proficiencies.skills.religion@1", "_dnd5e:effects.proficiencies.skills.survival@1"]}]}